benevalibre/__init__.py
benevalibre/__main__.py
benevalibre/api.py
benevalibre/apps.py
benevalibre/context_processors.py
benevalibre/menus.py
benevalibre/models.py
benevalibre/notifications.py
benevalibre/paginator.py
benevalibre/rules.py
benevalibre/signal_handlers.py
benevalibre/validators.py
benevalibre/viewsets.py
benevalibre/wsgi.py
benevalibre/accounts/__init__.py
benevalibre/accounts/apps.py
benevalibre/accounts/forms.py
benevalibre/accounts/models.py
benevalibre/accounts/urls.py
benevalibre/accounts/utils.py
benevalibre/accounts/migrations/0001_initial.py
benevalibre/accounts/migrations/0002_user_avatar.py
benevalibre/accounts/migrations/0003_user_avatar_stdimage.py
benevalibre/accounts/migrations/0004_user_anonymized.py
benevalibre/accounts/migrations/0005_alter_user_avatar.py
benevalibre/accounts/migrations/0006_alter_user_options.py
benevalibre/accounts/migrations/0007_rename_user_anonymized.py
benevalibre/accounts/migrations/0008_delete_old_user_thumbnails.py
benevalibre/accounts/migrations/0009_drop_registration_tables.py
benevalibre/accounts/migrations/0010_delete_anonymized_users.py
benevalibre/accounts/migrations/0011_remove_user_is_anonymized_user_theme_and_more.py
benevalibre/accounts/migrations/__init__.py
benevalibre/accounts/views/__init__.py
benevalibre/accounts/views/account.py
benevalibre/accounts/views/registration.py
benevalibre/associations/__init__.py
benevalibre/associations/api.py
benevalibre/associations/apps.py
benevalibre/associations/filters.py
benevalibre/associations/forms.py
benevalibre/associations/menus.py
benevalibre/associations/middleware.py
benevalibre/associations/migration.py
benevalibre/associations/rules.py
benevalibre/associations/tables.py
benevalibre/associations/urls.py
benevalibre/associations/migrations/0001_initial.py
benevalibre/associations/migrations/0002_create_default_data.py
benevalibre/associations/migrations/0003_add_unique_name_contraints.py
benevalibre/associations/migrations/__init__.py
benevalibre-2.0.1.dist-info/METADATA
benevalibre-2.0.1.dist-info/WHEEL
benevalibre-2.0.1.dist-info/licenses/CONTRIBUTORS.txt
benevalibre-2.0.1.dist-info/licenses/LICENSE
benevalibre-2.0.1.dist-info/RECORD
