Metadata-Version: 2.4
Name: benevalibre
Version: 2.0.1
Summary: Facilite la gestion et la valorisation du bénévolat dans les associations
Project-URL: Homepage, https://benevalibre.org
Project-URL: Documentation, https://docs.benevalibre.org
Project-URL: Repository, https://forge.cliss21.org/cliss21/benevalibre
Project-URL: Issues, https://forge.cliss21.org/cliss21/benevalibre/issues
Project-URL: Changelog, https://forge.cliss21.org/cliss21/benevalibre/src/branch/main/CHANGELOG.md
Author: Le comité de pilotage de Bénévalibre
Maintainer-email: Cliss XXI <contact@cliss21.com>
License-Expression: AGPL-3.0-or-later
License-File: CONTRIBUTORS.txt
License-File: LICENSE
Classifier: Development Status :: 5 - Production/Stable
Classifier: Environment :: Web Environment
Classifier: Framework :: Django :: 5.2
Classifier: Intended Audience :: Other Audience
Classifier: License :: OSI Approved :: GNU Affero General Public License v3
Classifier: Natural Language :: French
Classifier: Programming Language :: Python :: 3
Classifier: Programming Language :: Python :: 3.10
Classifier: Programming Language :: Python :: 3.11
Classifier: Programming Language :: Python :: 3.12
Classifier: Programming Language :: Python :: 3.13
Classifier: Topic :: Internet :: WWW/HTTP :: Dynamic Content
Requires-Python: >=3.10
Requires-Dist: django-cleanup~=9.0.0
Requires-Dist: django-cotton~=2.1.3
Requires-Dist: django-countries~=7.6.1
Requires-Dist: django-dynamic-filenames~=1.4.0
Requires-Dist: django-environ~=0.12.0
Requires-Dist: django-filter==25.1
Requires-Dist: django-ninja~=1.4.3
Requires-Dist: django-reversion~=5.1.0
Requires-Dist: django-tables2==2.7.5
Requires-Dist: django~=5.2.0
Requires-Dist: filetype~=1.2.0
Requires-Dist: packaging~=25.0
Requires-Dist: pillow>=6.2.1
Requires-Dist: requests~=2.32.4
Requires-Dist: rules~=3.5.0
Requires-Dist: sorl-thumbnail~=12.11.0
Requires-Dist: tablib[xlsx]~=3.8.0
